{
  "full_name": "Your Name",
  "email": "name@example.com",
  "github_username": "username",
  "project_name": "myproject",
  "project_slug": "{{ cookiecutter.project_name.lower().replace(' ', '-') }}",
  "module_name": "{{ cookiecutter.project_name.lower().replace(' ', '_').replace('-', '_') }}",
  "project_short_description": "a neat little project",
  "version": "0.1.0",
  "open_source_license": [
    "MIT license",
    "Apache Software License 2.0",
    "GNU General Public License v3.0",
    "GNU General Public License v2.0",
    "BSD 3-Clause 'New' or 'Revised' License",
    "GNU Lesser General Public License v2.1",
    "BSD 2-Clause 'Simplified' License",
    "Not open source"
  ]
}
